cursoFiap/__init__.py
cursoFiap/core.py
fiap_ia_simplemodule-1.0.0.dist-info/METADATA
fiap_ia_simplemodule-1.0.0.dist-info/WHEEL
fiap_ia_simplemodule-1.0.0.dist-info/top_level.txt
fiap_ia_simplemodule-1.0.0.dist-info/RECORD
