Metadata-Version: 2.4
Name: fiap-IA-SimpleModule
Version: 1.0.0
Summary: Lib pdo Curso FIAP de IA para DEV's
Home-page: https://github.com/ricardoHer/FIAP-IA-SimpleModule
Author: Ricardo Franco Hernandez
Author-email: ricardo.hern@icloud.com
License: MIT
Dynamic: author
Dynamic: author-email
Dynamic: description
Dynamic: description-content-type
Dynamic: home-page
Dynamic: license
Dynamic: summary
